multipartitegraph
